uaromanizer/__init__.py
uaromanizer/romanizer.py
uaromanizer/substitution.py
uaromanizer-0.0.2.dist-info/METADATA
uaromanizer-0.0.2.dist-info/WHEEL
uaromanizer-0.0.2.dist-info/licenses/LICENSE
uaromanizer-0.0.2.dist-info/RECORD
