Metadata-Version: 2.1
Name: uaromanizer
Version: 0.0.2
Summary: Romanization of Ukrainian writing
Project-URL: Homepage, https://github.com/m4rsm4ps/uaromanizer
Project-URL: Bug Tracker, https://github.com/m4rsm4ps/uaromanizer/issues
Author-email: Mars Maps <m4rsm4ps@gmail.com>
License: MIT License
Keywords: Ukrainian,romanization
Classifier: License :: OSI Approved :: MIT License
Classifier: Operating System :: OS Independent
Classifier: Programming Language :: Python :: 3
Requires-Python: >=3.7
